odoo/addons/l10n_ro_report_trial_balance/README.rst
odoo/addons/l10n_ro_report_trial_balance/__init__.py
odoo/addons/l10n_ro_report_trial_balance/__manifest__.py
odoo/addons/l10n_ro_report_trial_balance/report/__init__.py
odoo/addons/l10n_ro_report_trial_balance/report/abstract_report_xlsx.py
odoo/addons/l10n_ro_report_trial_balance/report/trial_balance.py
odoo/addons/l10n_ro_report_trial_balance/report/trial_balance_xlsx.py
odoo/addons/l10n_ro_report_trial_balance/static/description/icon.png
odoo/addons/l10n_ro_report_trial_balance/static/src/css/report.css
odoo/addons/l10n_ro_report_trial_balance/static/src/js/l10n_ro_report_trial_balance_backend.js
odoo/addons/l10n_ro_report_trial_balance/static/src/js/l10n_ro_report_trial_balance_widgets.js
odoo/addons/l10n_ro_report_trial_balance/tests/__init__.py
odoo/addons/l10n_ro_report_trial_balance/tests/abstract_test.py
odoo/addons/l10n_ro_report_trial_balance/tests/test_trial_balance.py
odoo/addons/l10n_ro_report_trial_balance/tests/test_trial_balance_abstract.py
odoo/addons/l10n_ro_report_trial_balance/views/layouts.xml
odoo/addons/l10n_ro_report_trial_balance/views/report_template.xml
odoo/addons/l10n_ro_report_trial_balance/views/report_trial_balance.xml
odoo/addons/l10n_ro_report_trial_balance/views/trial_balance.xml
odoo/addons/l10n_ro_report_trial_balance/views/trial_balance_view.xml
odoo/addons/l10n_ro_report_trial_balance/wizards/__init__.py
odoo/addons/l10n_ro_report_trial_balance/wizards/trial_balance_wizard.py
odoo/addons/l10n_ro_report_trial_balance/wizards/trial_balance_wizard_view.xml
odoo11_addon_l10n_ro_report_trial_balance-11.0.1.0.0.dist-info/DESCRIPTION.rst
odoo11_addon_l10n_ro_report_trial_balance-11.0.1.0.0.dist-info/METADATA
odoo11_addon_l10n_ro_report_trial_balance-11.0.1.0.0.dist-info/RECORD
odoo11_addon_l10n_ro_report_trial_balance-11.0.1.0.0.dist-info/WHEEL
odoo11_addon_l10n_ro_report_trial_balance-11.0.1.0.0.dist-info/metadata.json
odoo11_addon_l10n_ro_report_trial_balance-11.0.1.0.0.dist-info/top_level.txt
