Metadata-Version: 2.0
Name: odoo11-addon-l10n-ro-report-trial-balance
Version: 11.0.1.0.0
Summary: Romania - Account Trial Balance Report
Home-page: https://www.forbiom.eu
Author: Forest and Biomass Romania, Odoo Community Association (OCA)
Author-email: support@odoo-community.org
License: AGPL-3
Platform: UNKNOWN
Classifier: Programming Language :: Python
Classifier: Framework :: Odoo
Classifier: License :: OSI Approved :: GNU Affero General Public License v3
Requires-Python: >=2.7, !=3.0.*, !=3.1.*, !=3.2.*, !=3.3.*, !=3.4.*
Requires-Dist: odoo (<11.1dev,>=11.0a)
Requires-Dist: odoo11-addon-account-financial-report
